{
    "Ar36": {
        "error": 0.00015302667246363145,
        "error_type": "",
        "fit": "Bracketing Interpolate",
        "references": [
            {
                "exclude": "ok",
                "record_id": "ba-02-J-412",
                "uuid": "35757937-22e3-41df-93c5-83b0fdf46b32"
            },
            {
                "exclude": "ok",
                "record_id": "ba-02-J-413",
                "uuid": "fdbe6c77-6887-4511-873f-571afcdaf12e"
            },
            {
                "exclude": "ok",
                "record_id": "ba-02-J-414",
                "uuid": "3cb2d17d-7fa4-492d-98df-4d10e86c018f"
            },
            {
                "exclude": "ok",
                "record_id": "ba-02-J-415",
                "uuid": "b40beb52-46d9-4bb4-8bf3-ff2119f605d8"
            },
            {
                "exclude": "ok",
                "record_id": "ba-02-J-416",
                "uuid": "01e5b9a4-f315-493b-9fd9-2d3117165741"
            },
            {
                "exclude": "ok",
                "record_id": "ba-02-J-417",
                "uuid": "bba5da1c-e205-453a-95a8-49b39c75c9bb"
            },
            {
                "exclude": "ok",
                "record_id": "ba-02-J-418",
                "uuid": "e035c1c9-7c18-4179-a569-70de5ec31f50"
            }
        ],
        "reviewed": true,
        "value": 0.002338935865862564
    },
    "Ar37": {
        "error": 0.007029920652726997,
        "error_type": "",
        "fit": "Weighted Mean",
        "references": [
            {
                "exclude": "ok",
                "record_id": "ba-02-J-412",
                "uuid": "35757937-22e3-41df-93c5-83b0fdf46b32"
            },
            {
                "exclude": "ok",
                "record_id": "ba-02-J-413",
                "uuid": "fdbe6c77-6887-4511-873f-571afcdaf12e"
            },
            {
                "exclude": "ok",
                "record_id": "ba-02-J-414",
                "uuid": "3cb2d17d-7fa4-492d-98df-4d10e86c018f"
            },
            {
                "exclude": "ok",
                "record_id": "ba-02-J-415",
                "uuid": "b40beb52-46d9-4bb4-8bf3-ff2119f605d8"
            },
            {
                "exclude": "ok",
                "record_id": "ba-02-J-416",
                "uuid": "01e5b9a4-f315-493b-9fd9-2d3117165741"
            },
            {
                "exclude": "ok",
                "record_id": "ba-02-J-417",
                "uuid": "bba5da1c-e205-453a-95a8-49b39c75c9bb"
            },
            {
                "exclude": "ok",
                "record_id": "ba-02-J-418",
                "uuid": "e035c1c9-7c18-4179-a569-70de5ec31f50"
            }
        ],
        "reviewed": true,
        "value": 0.03611938003953305
    },
    "Ar38": {
        "error": 0.011172865962337736,
        "error_type": "",
        "fit": "Weighted Mean",
        "references": [
            {
                "exclude": "ok",
                "record_id": "ba-02-J-412",
                "uuid": "35757937-22e3-41df-93c5-83b0fdf46b32"
            },
            {
                "exclude": "ok",
                "record_id": "ba-02-J-413",
                "uuid": "fdbe6c77-6887-4511-873f-571afcdaf12e"
            },
            {
                "exclude": "ok",
                "record_id": "ba-02-J-414",
                "uuid": "3cb2d17d-7fa4-492d-98df-4d10e86c018f"
            },
            {
                "exclude": "ok",
                "record_id": "ba-02-J-415",
                "uuid": "b40beb52-46d9-4bb4-8bf3-ff2119f605d8"
            },
            {
                "exclude": "ok",
                "record_id": "ba-02-J-416",
                "uuid": "01e5b9a4-f315-493b-9fd9-2d3117165741"
            },
            {
                "exclude": "ok",
                "record_id": "ba-02-J-417",
                "uuid": "bba5da1c-e205-453a-95a8-49b39c75c9bb"
            },
            {
                "exclude": "ok",
                "record_id": "ba-02-J-418",
                "uuid": "e035c1c9-7c18-4179-a569-70de5ec31f50"
            }
        ],
        "reviewed": true,
        "value": 0.00501460882412499
    },
    "Ar39": {
        "error": 0.010862635866045066,
        "error_type": "",
        "fit": "Weighted Mean",
        "references": [
            {
                "exclude": "ok",
                "record_id": "ba-02-J-412",
                "uuid": "35757937-22e3-41df-93c5-83b0fdf46b32"
            },
            {
                "exclude": "ok",
                "record_id": "ba-02-J-413",
                "uuid": "fdbe6c77-6887-4511-873f-571afcdaf12e"
            },
            {
                "exclude": "ok",
                "record_id": "ba-02-J-414",
                "uuid": "3cb2d17d-7fa4-492d-98df-4d10e86c018f"
            },
            {
                "exclude": "ok",
                "record_id": "ba-02-J-415",
                "uuid": "b40beb52-46d9-4bb4-8bf3-ff2119f605d8"
            },
            {
                "exclude": "ok",
                "record_id": "ba-02-J-416",
                "uuid": "01e5b9a4-f315-493b-9fd9-2d3117165741"
            },
            {
                "exclude": "ok",
                "record_id": "ba-02-J-417",
                "uuid": "bba5da1c-e205-453a-95a8-49b39c75c9bb"
            },
            {
                "exclude": "ok",
                "record_id": "ba-02-J-418",
                "uuid": "e035c1c9-7c18-4179-a569-70de5ec31f50"
            }
        ],
        "reviewed": true,
        "value": 0.04169083827773537
    },
    "Ar40": {
        "error": 0.008939171625703702,
        "error_type": "",
        "fit": "Bracketing Interpolate",
        "references": [
            {
                "exclude": "ok",
                "record_id": "ba-02-J-412",
                "uuid": "35757937-22e3-41df-93c5-83b0fdf46b32"
            },
            {
                "exclude": "ok",
                "record_id": "ba-02-J-413",
                "uuid": "fdbe6c77-6887-4511-873f-571afcdaf12e"
            },
            {
                "exclude": "ok",
                "record_id": "ba-02-J-414",
                "uuid": "3cb2d17d-7fa4-492d-98df-4d10e86c018f"
            },
            {
                "exclude": "ok",
                "record_id": "ba-02-J-415",
                "uuid": "b40beb52-46d9-4bb4-8bf3-ff2119f605d8"
            },
            {
                "exclude": "ok",
                "record_id": "ba-02-J-416",
                "uuid": "01e5b9a4-f315-493b-9fd9-2d3117165741"
            },
            {
                "exclude": "ok",
                "record_id": "ba-02-J-417",
                "uuid": "bba5da1c-e205-453a-95a8-49b39c75c9bb"
            },
            {
                "exclude": "ok",
                "record_id": "ba-02-J-418",
                "uuid": "e035c1c9-7c18-4179-a569-70de5ec31f50"
            }
        ],
        "reviewed": true,
        "value": 0.092072894142173
    },
    "Ar41": {
        "error": 0.005726250774519531,
        "error_type": "",
        "fit": "previous",
        "references": [
            {
                "exclude": false,
                "record_id": "ba-02-J-413"
            }
        ],
        "value": 0.018312745908291232
    }
}