{
    "AX": {
        "error": 0.009358845171688366,
        "error_type": "SEM",
        "filter_outliers_dict": {
            "filter_outliers": true,
            "iterations": 1,
            "std_devs": 2
        },
        "fit": "Average",
        "fn": 44,
        "include_baseline_error": false,
        "n": 45,
        "reviewed": true,
        "value": -0.001078429981134832
    },
    "CDD": {
        "error": 1.4627427459977744e-05,
        "error_type": "SEM",
        "filter_outliers_dict": {
            "filter_outliers": true,
            "iterations": 1,
            "std_devs": 10
        },
        "fit": "Average",
        "fn": 45,
        "include_baseline_error": false,
        "n": 45,
        "reviewed": true,
        "value": 5.408174151347743e-05
    },
    "H1": {
        "error": 0.006441699746988045,
        "error_type": "SEM",
        "filter_outliers_dict": {
            "filter_outliers": true,
            "iterations": 1,
            "std_devs": 2
        },
        "fit": "Average",
        "fn": 44,
        "include_baseline_error": false,
        "n": 45,
        "reviewed": true,
        "value": 0.05532410569867352
    },
    "H2": {
        "error": 0.006199220937612247,
        "error_type": "SEM",
        "filter_outliers_dict": {
            "filter_outliers": true,
            "iterations": 1,
            "std_devs": 2
        },
        "fit": "average",
        "value": 0.015744595184960124
    },
    "L1": {
        "error": 0.0015804661018545506,
        "error_type": "SEM",
        "filter_outliers_dict": {
            "filter_outliers": true,
            "iterations": 1,
            "std_devs": 2
        },
        "fit": "Average",
        "fn": 45,
        "include_baseline_error": false,
        "n": 45,
        "reviewed": true,
        "value": 0.027973301232688957
    },
    "L2": {
        "error": 0.006597344701419845,
        "error_type": "SEM",
        "filter_outliers_dict": {
            "filter_outliers": true,
            "iterations": 1,
            "std_devs": 2
        },
        "fit": "Average",
        "fn": 43,
        "include_baseline_error": false,
        "n": 45,
        "reviewed": true,
        "value": 0.06374901445138506
    }
}