{
    "Ar36": {
        "error": 0.002047761884363441,
        "error_type": "SEM",
        "filter_outliers_dict": {
            "filter_outliers": true,
            "iterations": 1,
            "std_devs": 2
        },
        "fit": "Parabolic",
        "fn": 271,
        "include_baseline_error": false,
        "n": 280,
        "reviewed": true,
        "value": 0.7561302522036302
    },
    "Ar37": {
        "error": 0.005728706186113291,
        "error_type": "SEM",
        "filter_outliers_dict": {
            "filter_outliers": true,
            "iterations": 1,
            "std_devs": 2
        },
        "fit": "Linear",
        "fn": 266,
        "include_baseline_error": false,
        "n": 280,
        "reviewed": true,
        "value": 0.08413979373282576
    },
    "Ar38": {
        "error": 0.001818982683007226,
        "error_type": "SEM",
        "filter_outliers_dict": {
            "filter_outliers": true,
            "iterations": 1,
            "std_devs": 2
        },
        "fit": "Linear",
        "fn": 266,
        "include_baseline_error": false,
        "n": 280,
        "reviewed": true,
        "value": 0.1844684587024077
    },
    "Ar39": {
        "error": 0.010726778098997636,
        "error_type": "SEM",
        "filter_outliers_dict": {
            "filter_outliers": true,
            "iterations": 1,
            "std_devs": 2
        },
        "fit": "Parabolic",
        "fn": 272,
        "include_baseline_error": false,
        "n": 280,
        "reviewed": true,
        "value": -0.006514613541668454
    },
    "Ar40": {
        "error": 0.024793085014598298,
        "error_type": "SEM",
        "filter_outliers_dict": {
            "filter_outliers": true,
            "iterations": 1,
            "std_devs": 2
        },
        "fit": "Parabolic",
        "fn": 267,
        "include_baseline_error": false,
        "n": 280,
        "reviewed": true,
        "value": 224.7305561719544
    },
    "Ar41": {
        "error": 0.005636288650134651,
        "error_type": "SEM",
        "filter_outliers_dict": {
            "filter_outliers": true,
            "iterations": 1,
            "std_devs": 2
        },
        "fit": "linear",
        "value": 0.04634405338088846
    }
}